docarray/__init__.py
docarray/array/__init__.py
docarray/array/any_array.py
docarray/array/doc_list/__init__.py
docarray/array/doc_list/doc_list.py
docarray/array/doc_list/io.py
docarray/array/doc_list/pushpull.py
docarray/array/doc_vec/__init__.py
docarray/array/doc_vec/column_storage.py
docarray/array/doc_vec/doc_vec.py
docarray/array/doc_vec/io.py
docarray/array/list_advance_indexing.py
docarray/base_doc/__init__.py
docarray/base_doc/any_doc.py
docarray/base_doc/base_node.py
docarray/base_doc/doc.py
docarray/base_doc/docarray_response.py
docarray/base_doc/io/__init__.py
docarray/base_doc/io/json.py
docarray/base_doc/mixins/__init__.py
docarray/base_doc/mixins/io.py
docarray/base_doc/mixins/update.py
docarray/computation/__init__.py
docarray/computation/abstract_comp_backend.py
docarray/computation/abstract_numpy_based_backend.py
docarray/computation/jax_backend.py
docarray/computation/numpy_backend.py
docarray/computation/tensorflow_backend.py
docarray/computation/torch_backend.py
docarray/data/__init__.py
docarray/data/torch_dataset.py
docarray/display/__init__.py
docarray/display/document_array_summary.py
docarray/display/document_summary.py
docarray/display/tensor_display.py
docarray/documents/__init__.py
docarray/documents/audio.py
docarray/documents/helper.py
docarray/documents/image.py
docarray/documents/legacy/__init__.py
docarray/documents/legacy/legacy_document.py
docarray/documents/mesh/__init__.py
docarray/documents/mesh/mesh_3d.py
docarray/documents/mesh/vertices_and_faces.py
docarray/documents/point_cloud/__init__.py
docarray/documents/point_cloud/point_cloud_3d.py
docarray/documents/point_cloud/points_and_colors.py
docarray/documents/text.py
docarray/documents/video.py
docarray/exceptions/__init__.py
docarray/exceptions/exceptions.py
docarray/helper.py
docarray/index/__init__.py
docarray/index/abstract.py
docarray/index/backends/__init__.py
docarray/index/backends/elastic.py
docarray/index/backends/elasticv7.py
docarray/index/backends/helper.py
docarray-0.39.1.dist-info/LICENSE.md
docarray-0.39.1.dist-info/METADATA
docarray-0.39.1.dist-info/WHEEL
docarray-0.39.1.dist-info/RECORD
