Metadata-Version: 2.1
Name: docarray
Version: 0.39.1
Summary: The data structure for multimodal data
Home-page: https://docs.docarray.org/
License: Apache 2.0
Keywords: docarray,deep-learning,data-structures cross-modal multi-modal, unstructured-data, nested-data,neural-search
Author: DocArray
Requires-Python: >=3.8,<4.0
Classifier: Development Status :: 5 - Production/Stable
Classifier: Environment :: Console
Classifier: Intended Audience :: Developers
Classifier: Intended Audience :: Education
Classifier: Intended Audience :: Science/Research
Classifier: License :: OSI Approved :: Apache Software License
Classifier: License :: Other/Proprietary License
Classifier: Operating System :: OS Independent
Classifier: Programming Language :: Python :: 3
Classifier: Programming Language :: Python :: 3.8
Classifier: Programming Language :: Python :: 3.9
Classifier: Programming Language :: Python :: 3.10
Classifier: Programming Language :: Python :: 3.11
Classifier: Programming Language :: Unix Shell
Classifier: Topic :: Database :: Database Engines/Servers
Classifier: Topic :: Internet :: WWW/HTTP :: Indexing/Search
Classifier: Topic :: Multimedia :: Video
Classifier: Topic :: Scientific/Engineering
Classifier: Topic :: Scientific/Engineering :: Artificial Intelligence
Classifier: Topic :: Scientific/Engineering :: Image Recognition
Classifier: Topic :: Scientific/Engineering :: Mathematics
Classifier: Topic :: Software Development
Classifier: Topic :: Software Development :: Libraries
Classifier: Topic :: Software Development :: Libraries :: Python Modules
Provides-Extra: audio
Provides-Extra: aws
Provides-Extra: elasticsearch
Provides-Extra: full
Provides-Extra: hnswlib
Provides-Extra: image
Provides-Extra: jac
Provides-Extra: jax
Provides-Extra: mesh
Provides-Extra: milvus
Provides-Extra: pandas
Provides-Extra: proto
Provides-Extra: qdrant
Provides-Extra: redis
Provides-Extra: torch
Provides-Extra: video
Provides-Extra: weaviate
Provides-Extra: web
Requires-Dist: av (>=10.0.0) ; extra == "video" or extra == "full"
Requires-Dist: elastic-transport (>=8.4.0,<9.0.0) ; extra == "elasticsearch"
Requires-Dist: elasticsearch (>=7.10.1) ; extra == "elasticsearch"
Requires-Dist: fastapi (>=0.100.0) ; extra == "web"
Requires-Dist: hnswlib (>=0.7.0) ; extra == "hnswlib"
Requires-Dist: jax (>=0.4.10) ; extra == "jax" or extra == "full"
Requires-Dist: jina-hubble-sdk (>=0.34.0) ; extra == "jac"
Requires-Dist: lz4 (>=1.0.0) ; extra == "proto" or extra == "full"
Requires-Dist: numpy (>=1.17.3)
Requires-Dist: orjson (>=3.8.2)
Requires-Dist: pandas (>=1.1.0) ; extra == "pandas" or extra == "full"
Requires-Dist: pillow (>=9.3.0) ; extra == "image" or extra == "full"
Requires-Dist: protobuf (>=3.20.0) ; extra == "proto" or extra == "hnswlib" or extra == "full"
Requires-Dist: pydantic (>=1.10.8)
Requires-Dist: pydub (>=0.25.1,<0.26.0) ; extra == "audio" or extra == "full"
Requires-Dist: pymilvus (>=2.2.12,<3.0.0) ; extra == "milvus"
Requires-Dist: qdrant-client (>=1.4.0) ; (python_version < "3.12") and (extra == "qdrant")
Requires-Dist: redis (>=4.6.0,<5.0.0) ; extra == "redis"
Requires-Dist: rich (>=13.1.0)
Requires-Dist: smart-open[s3] (>=6.3.0) ; extra == "aws"
Requires-Dist: torch (>=1.0.0) ; extra == "torch"
Requires-Dist: trimesh[easy] (>=3.17.1) ; extra == "mesh" or extra == "full"
Requires-Dist: types-pillow (>=9.3.0.1) ; extra == "image" or extra == "full"
Requires-Dist: types-requests (>=2.28.11.6)
Requires-Dist: typing-inspect (>=0.8.0)
Requires-Dist: weaviate-client (>=3.17,<3.18) ; extra == "weaviate"
Project-URL: Documentation, https://docs.docarray.org
Project-URL: Repository, https://github.com/docarray/docarray
